{
   "status":"OK",
   "copyright":"Copyright (c) 2016 The New York Times Company.  All Rights Reserved.",
   "num_results":10,
   "results":[
      {
         "nyt_movie_id":462175,
         "display_title":"Godzilla",
         "sort_name":"Godzilla",
         "mpaa_rating":"PG13",
         "critics_pick":0,
         "thousand_best":"0",
         "byline":"A. O. Scott",
         "headline":"Still Radioactive and Spoiling for a Fight",
         "capsule_review":"",
         "summary_short":"",
         "publication_date":"2014-05-16",
         "opening_date":"2014-05-16",
         "dvd_release_date":null,
         "date_updated":"2015-08-28 11:55:50",
         "seo_name":"Godzilla",
         "link":{
            "type":"article",
            "url":"http:\/\/movies.nytimes.com\/2014\/05\/16\/movies\/godzilla-grandaddy-of-movie-monsters-stomps-back.html",
            "suggested_link_text":"Read the New York Times Review of Godzilla"
         },
         "related_urls":[
            {
               "type":"overview",
               "url":"http:\/\/movies.nytimes.com\/movie\/462175\/Godzilla\/overview",
               "suggested_link_text":"Overview of Godzilla"
            },
            {
               "type":"showtimes",
               "url":"http:\/\/movies.nytimes.com\/movie\/462175\/Godzilla\/showtimes",
               "suggested_link_text":"Tickets & Showtimes for Godzilla"
            },
            {
               "type":"awards",
               "url":"http:\/\/movies.nytimes.com\/movie\/462175\/Godzilla\/details",
               "suggested_link_text":"Cast, Credits & Awards for Godzilla"
            },
            {
               "type":"community",
               "url":"http:\/\/movies.nytimes.com\/movie\/462175\/Godzilla\/rnr",
               "suggested_link_text":"Readers' Reviews of Godzilla"
            },
            {
               "type":"trailers",
               "url":"http:\/\/movies.nytimes.com\/movie\/462175\/Godzilla\/trailers",
               "suggested_link_text":"Trailers & Clips for Godzilla"
            }
         ],
         "multimedia":{
            "resource":{
               "type":"thumbnail",
               "src":"http:\/\/graphics8.nytimes.com\/images\/2014\/05\/16\/arts\/16GODZILLA\/16GODZILLA-thumbStandard-v2.jpg",
               "height":75,
               "width":75
            }
         }
      },
      {
         "nyt_movie_id":162465,
         "display_title":"Godzilla",
         "sort_name":"Godzilla",
         "mpaa_rating":"PG13",
         "critics_pick":0,
         "thousand_best":"0",
         "byline":"Stephen Holden",
         "headline":"",
         "capsule_review":"Giant mutant lizard wreaks havoc on New York. Big beast, little movie.",
         "summary_short":"",
         "publication_date":"1998-05-19",
         "opening_date":"1998-05-20",
         "dvd_release_date":null,
         "date_updated":"2010-08-25 14:47:08",
         "seo_name":"Godzilla",
         "link":{
            "type":"article",
            "url":"http:\/\/movies.nytimes.com\/movie\/review?res=9E06E4DB1639F93AA25756C0A96E958260",
            "suggested_link_text":"Read the New York Times Review of Godzilla"
         },
         "related_urls":[
            {
               "type":"overview",
               "url":"http:\/\/movies.nytimes.com\/movie\/162465\/Godzilla\/overview",
               "suggested_link_text":"Overview of Godzilla"
            },
            {
               "type":"showtimes",
               "url":"http:\/\/movies.nytimes.com\/movie\/162465\/Godzilla\/showtimes",
               "suggested_link_text":"Tickets & Showtimes for Godzilla"
            },
            {
               "type":"awards",
               "url":"http:\/\/movies.nytimes.com\/movie\/162465\/Godzilla\/details",
               "suggested_link_text":"Cast, Credits & Awards for Godzilla"
            },
            {
               "type":"community",
               "url":"http:\/\/movies.nytimes.com\/movie\/162465\/Godzilla\/rnr",
               "suggested_link_text":"Readers' Reviews of Godzilla"
            },
            {
               "type":"trailers",
               "url":"http:\/\/movies.nytimes.com\/movie\/162465\/Godzilla\/trailers",
               "suggested_link_text":"Trailers & Clips for Godzilla"
            }
         ]
      },
      {
         "nyt_movie_id":20103,
         "display_title":"Godzilla",
         "sort_name":"Godzilla",
         "mpaa_rating":null,
         "critics_pick":0,
         "thousand_best":"0",
         "byline":"BOSLEY CROWTHER",
         "headline":"",
         "capsule_review":"Makes Kong look like a runt, but not his picture.",
         "summary_short":"",
         "publication_date":"1956-04-28",
         "opening_date":"1956-04-27",
         "dvd_release_date":null,
         "date_updated":"2010-08-25 14:47:08",
         "seo_name":"Godzilla",
         "link":{
            "type":"article",
            "url":"http:\/\/movies.nytimes.com\/movie\/review?res=9A05E6DD1F3BE23ABC4051DFB266838D649EDE",
            "suggested_link_text":"Read the New York Times Review of Godzilla"
         },
         "related_urls":[
            {
               "type":"overview",
               "url":"http:\/\/movies.nytimes.com\/movie\/20103\/Godzilla\/overview",
               "suggested_link_text":"Overview of Godzilla"
            },
            {
               "type":"showtimes",
               "url":"http:\/\/movies.nytimes.com\/movie\/20103\/Godzilla\/showtimes",
               "suggested_link_text":"Tickets & Showtimes for Godzilla"
            },
            {
               "type":"awards",
               "url":"http:\/\/movies.nytimes.com\/movie\/20103\/Godzilla\/details",
               "suggested_link_text":"Cast, Credits & Awards for Godzilla"
            },
            {
               "type":"community",
               "url":"http:\/\/movies.nytimes.com\/movie\/20103\/Godzilla\/rnr",
               "suggested_link_text":"Readers' Reviews of Godzilla"
            },
            {
               "type":"trailers",
               "url":"http:\/\/movies.nytimes.com\/movie\/20103\/Godzilla\/trailers",
               "suggested_link_text":"Trailers & Clips for Godzilla"
            }
         ]
      },
      {
         "nyt_movie_id":196447,
         "display_title":"Godzilla 2000",
         "sort_name":"Godzilla 2000",
         "mpaa_rating":"PG",
         "critics_pick":0,
         "thousand_best":"0",
         "byline":"STEPHEN HOLDEN",
         "headline":"",
         "capsule_review":"Giant lizard protects Japan from U.F.O. Dubbed in English.",
         "summary_short":"",
         "publication_date":"2000-08-18",
         "opening_date":"2000-08-18",
         "dvd_release_date":null,
         "date_updated":"2010-08-25 14:47:08",
         "seo_name":"Godzilla-2000",
         "link":{
            "type":"article",
            "url":"http:\/\/movies.nytimes.com\/movie\/review?res=9D0CEFDE143EF93BA2575BC0A9669C8B63",
            "suggested_link_text":"Read the New York Times Review of Godzilla 2000"
         },
         "related_urls":[
            {
               "type":"overview",
               "url":"http:\/\/movies.nytimes.com\/movie\/196447\/Godzilla-2000\/overview",
               "suggested_link_text":"Overview of Godzilla 2000"
            },
            {
               "type":"showtimes",
               "url":"http:\/\/movies.nytimes.com\/movie\/196447\/Godzilla-2000\/showtimes",
               "suggested_link_text":"Tickets & Showtimes for Godzilla 2000"
            },
            {
               "type":"awards",
               "url":"http:\/\/movies.nytimes.com\/movie\/196447\/Godzilla-2000\/details",
               "suggested_link_text":"Cast, Credits & Awards for Godzilla 2000"
            },
            {
               "type":"community",
               "url":"http:\/\/movies.nytimes.com\/movie\/196447\/Godzilla-2000\/rnr",
               "suggested_link_text":"Readers' Reviews of Godzilla 2000"
            },
            {
               "type":"trailers",
               "url":"http:\/\/movies.nytimes.com\/movie\/196447\/Godzilla-2000\/trailers",
               "suggested_link_text":"Trailers & Clips for Godzilla 2000"
            }
         ]
      },
      {
         "nyt_movie_id":20091,
         "display_title":"Gojira",
         "sort_name":"Gojira",
         "mpaa_rating":null,
         "critics_pick":0,
         "thousand_best":"0",
         "byline":"Vincent Canby",
         "headline":"",
         "capsule_review":"Behave yourself, big boy.",
         "summary_short":"",
         "publication_date":"1985-08-30",
         "opening_date":"1985-08-01",
         "dvd_release_date":null,
         "date_updated":"2010-08-25 14:47:08",
         "seo_name":"Gojira",
         "link":{
            "type":"article",
            "url":"http:\/\/movies.nytimes.com\/movie\/review?res=9F06E1DB143BF933A0575BC0A963948260",
            "suggested_link_text":"Read the New York Times Review of Gojira"
         },
         "related_urls":[
            {
               "type":"overview",
               "url":"http:\/\/movies.nytimes.com\/movie\/20091\/Gojira\/overview",
               "suggested_link_text":"Overview of Gojira"
            },
            {
               "type":"showtimes",
               "url":"http:\/\/movies.nytimes.com\/movie\/20091\/Gojira\/showtimes",
               "suggested_link_text":"Tickets & Showtimes for Gojira"
            },
            {
               "type":"awards",
               "url":"http:\/\/movies.nytimes.com\/movie\/20091\/Gojira\/details",
               "suggested_link_text":"Cast, Credits & Awards for Gojira"
            },
            {
               "type":"community",
               "url":"http:\/\/movies.nytimes.com\/movie\/20091\/Gojira\/rnr",
               "suggested_link_text":"Readers' Reviews of Gojira"
            },
            {
               "type":"trailers",
               "url":"http:\/\/movies.nytimes.com\/movie\/20091\/Gojira\/trailers",
               "suggested_link_text":"Trailers & Clips for Gojira"
            }
         ]
      },
      {
         "nyt_movie_id":20101,
         "display_title":"Godzilla Versus The Smog Monster",
         "sort_name":"Godzilla Versus The Smog Monster",
         "mpaa_rating":null,
         "critics_pick":0,
         "thousand_best":"0",
         "byline":"VINCENT CANBY",
         "headline":"",
         "capsule_review":"Last tango in Tokyo.",
         "summary_short":"",
         "publication_date":"1972-07-06",
         "opening_date":null,
         "dvd_release_date":null,
         "date_updated":"2010-08-25 14:47:08",
         "seo_name":"Godzilla-Versus-The-Smog-Monster",
         "link":{
            "type":"article",
            "url":"http:\/\/movies.nytimes.com\/movie\/review?res=9D0DE2DA1F3EE63BBC4E53DFB1668389669EDE",
            "suggested_link_text":"Read the New York Times Review of Godzilla Versus The Smog Monster"
         },
         "related_urls":[
            {
               "type":"overview",
               "url":"http:\/\/movies.nytimes.com\/movie\/20101\/Godzilla-Versus-The-Smog-Monster\/overview",
               "suggested_link_text":"Overview of Godzilla Versus The Smog Monster"
            },
            {
               "type":"showtimes",
               "url":"http:\/\/movies.nytimes.com\/movie\/20101\/Godzilla-Versus-The-Smog-Monster\/showtimes",
               "suggested_link_text":"Tickets & Showtimes for Godzilla Versus The Smog Monster"
            },
            {
               "type":"awards",
               "url":"http:\/\/movies.nytimes.com\/movie\/20101\/Godzilla-Versus-The-Smog-Monster\/details",
               "suggested_link_text":"Cast, Credits & Awards for Godzilla Versus The Smog Monster"
            },
            {
               "type":"community",
               "url":"http:\/\/movies.nytimes.com\/movie\/20101\/Godzilla-Versus-The-Smog-Monster\/rnr",
               "suggested_link_text":"Readers' Reviews of Godzilla Versus The Smog Monster"
            },
            {
               "type":"trailers",
               "url":"http:\/\/movies.nytimes.com\/movie\/20101\/Godzilla-Versus-The-Smog-Monster\/trailers",
               "suggested_link_text":"Trailers & Clips for Godzilla Versus The Smog Monster"
            }
         ]
      },
      {
         "nyt_movie_id":132979,
         "display_title":"Bambi Meets Godzilla",
         "sort_name":"Bambi Meets Godzilla",
         "mpaa_rating":"",
         "critics_pick":0,
         "thousand_best":"0",
         "byline":"LAWRENCE VAN GELDER",
         "headline":"",
         "capsule_review":"",
         "summary_short":"",
         "publication_date":"1977-08-18",
         "opening_date":null,
         "dvd_release_date":null,
         "date_updated":"2010-08-25 14:47:08",
         "seo_name":"Bambi-Meets-Godzilla",
         "link":{
            "type":"article",
            "url":"http:\/\/movies.nytimes.com\/movie\/review?res=980DE7DE1E3FE334BC4052DFBE66838C669EDE",
            "suggested_link_text":"Read the New York Times Review of Bambi Meets Godzilla"
         },
         "related_urls":[
            {
               "type":"overview",
               "url":"http:\/\/movies.nytimes.com\/movie\/132979\/Bambi-Meets-Godzilla\/overview",
               "suggested_link_text":"Overview of Bambi Meets Godzilla"
            },
            {
               "type":"showtimes",
               "url":"http:\/\/movies.nytimes.com\/movie\/132979\/Bambi-Meets-Godzilla\/showtimes",
               "suggested_link_text":"Tickets & Showtimes for Bambi Meets Godzilla"
            },
            {
               "type":"awards",
               "url":"http:\/\/movies.nytimes.com\/movie\/132979\/Bambi-Meets-Godzilla\/details",
               "suggested_link_text":"Cast, Credits & Awards for Bambi Meets Godzilla"
            },
            {
               "type":"community",
               "url":"http:\/\/movies.nytimes.com\/movie\/132979\/Bambi-Meets-Godzilla\/rnr",
               "suggested_link_text":"Readers' Reviews of Bambi Meets Godzilla"
            },
            {
               "type":"trailers",
               "url":"http:\/\/movies.nytimes.com\/movie\/132979\/Bambi-Meets-Godzilla\/trailers",
               "suggested_link_text":"Trailers & Clips for Bambi Meets Godzilla"
            }
         ]
      },
      {
         "nyt_movie_id":19624,
         "display_title":"Ghidorah: The Three-Headed Monster",
         "sort_name":"Ghidorah: The Three-Headed Monster",
         "mpaa_rating":"",
         "critics_pick":0,
         "thousand_best":"0",
         "byline":"VINCENT CANBY.",
         "headline":"",
         "capsule_review":"Curly, Larry and Moe, Japanese-style.",
         "summary_short":"",
         "publication_date":"1965-12-16",
         "opening_date":null,
         "dvd_release_date":null,
         "date_updated":"2010-08-25 14:47:08",
         "seo_name":"Ghidorah-The-Three-Headed-Monster",
         "link":{
            "type":"article",
            "url":"http:\/\/movies.nytimes.com\/movie\/review?res=9906E2DF1430E33ABC4E52DFB467838E679EDE",
            "suggested_link_text":"Read the New York Times Review of Ghidorah: The Three-Headed Monster"
         },
         "related_urls":[
            {
               "type":"overview",
               "url":"http:\/\/movies.nytimes.com\/movie\/19624\/Ghidorah-The-Three-Headed-Monster\/overview",
               "suggested_link_text":"Overview of Ghidorah: The Three-Headed Monster"
            },
            {
               "type":"showtimes",
               "url":"http:\/\/movies.nytimes.com\/movie\/19624\/Ghidorah-The-Three-Headed-Monster\/showtimes",
               "suggested_link_text":"Tickets & Showtimes for Ghidorah: The Three-Headed Monster"
            },
            {
               "type":"awards",
               "url":"http:\/\/movies.nytimes.com\/movie\/19624\/Ghidorah-The-Three-Headed-Monster\/details",
               "suggested_link_text":"Cast, Credits & Awards for Ghidorah: The Three-Headed Monster"
            },
            {
               "type":"community",
               "url":"http:\/\/movies.nytimes.com\/movie\/19624\/Ghidorah-The-Three-Headed-Monster\/rnr",
               "suggested_link_text":"Readers' Reviews of Ghidorah: The Three-Headed Monster"
            },
            {
               "type":"trailers",
               "url":"http:\/\/movies.nytimes.com\/movie\/19624\/Ghidorah-The-Three-Headed-Monster\/trailers",
               "suggested_link_text":"Trailers & Clips for Ghidorah: The Three-Headed Monster"
            }
         ]
      },
      {
         "nyt_movie_id":93411,
         "display_title":"Godzilla Versus The Thing",
         "sort_name":"Godzilla Versus The Thing",
         "mpaa_rating":null,
         "critics_pick":0,
         "thousand_best":"0",
         "byline":"EUGENE ARCHER",
         "headline":"",
         "capsule_review":"Tango for two titans. Help yourself.",
         "summary_short":"",
         "publication_date":"1964-11-26",
         "opening_date":null,
         "dvd_release_date":null,
         "date_updated":"2010-08-25 14:47:08",
         "seo_name":"Godzilla-Versus-The-Thing",
         "link":{
            "type":"article",
            "url":"http:\/\/movies.nytimes.com\/movie\/review?res=9A06E2DD123CEE32A25755C2A9679D946591D6CF",
            "suggested_link_text":"Read the New York Times Review of Godzilla Versus The Thing"
         },
         "related_urls":[
            {
               "type":"overview",
               "url":"http:\/\/movies.nytimes.com\/movie\/93411\/Godzilla-Versus-The-Thing\/overview",
               "suggested_link_text":"Overview of Godzilla Versus The Thing"
            },
            {
               "type":"showtimes",
               "url":"http:\/\/movies.nytimes.com\/movie\/93411\/Godzilla-Versus-The-Thing\/showtimes",
               "suggested_link_text":"Tickets & Showtimes for Godzilla Versus The Thing"
            },
            {
               "type":"awards",
               "url":"http:\/\/movies.nytimes.com\/movie\/93411\/Godzilla-Versus-The-Thing\/details",
               "suggested_link_text":"Cast, Credits & Awards for Godzilla Versus The Thing"
            },
            {
               "type":"community",
               "url":"http:\/\/movies.nytimes.com\/movie\/93411\/Godzilla-Versus-The-Thing\/rnr",
               "suggested_link_text":"Readers' Reviews of Godzilla Versus The Thing"
            },
            {
               "type":"trailers",
               "url":"http:\/\/movies.nytimes.com\/movie\/93411\/Godzilla-Versus-The-Thing\/trailers",
               "suggested_link_text":"Trailers & Clips for Godzilla Versus The Thing"
            }
         ]
      },
      {
         "nyt_movie_id":27394,
         "display_title":"King Kong vs. Godzilla",
         "sort_name":"King Kong vs. Godzilla",
         "mpaa_rating":"",
         "critics_pick":0,
         "thousand_best":"0",
         "byline":"BOSLEY CROWTHER",
         "headline":"",
         "capsule_review":"Duck.",
         "summary_short":"",
         "publication_date":"1963-06-27",
         "opening_date":null,
         "dvd_release_date":null,
         "date_updated":"2010-08-25 14:47:08",
         "seo_name":"King-Kong-vs-Godzilla",
         "link":{
            "type":"article",
            "url":"http:\/\/movies.nytimes.com\/movie\/review?res=9D04E5DF1139E43BBC4F51DFB0668388679EDE",
            "suggested_link_text":"Read the New York Times Review of King Kong vs. Godzilla"
         },
         "related_urls":[
            {
               "type":"overview",
               "url":"http:\/\/movies.nytimes.com\/movie\/27394\/King-Kong-vs-Godzilla\/overview",
               "suggested_link_text":"Overview of King Kong vs. Godzilla"
            },
            {
               "type":"showtimes",
               "url":"http:\/\/movies.nytimes.com\/movie\/27394\/King-Kong-vs-Godzilla\/showtimes",
               "suggested_link_text":"Tickets & Showtimes for King Kong vs. Godzilla"
            },
            {
               "type":"awards",
               "url":"http:\/\/movies.nytimes.com\/movie\/27394\/King-Kong-vs-Godzilla\/details",
               "suggested_link_text":"Cast, Credits & Awards for King Kong vs. Godzilla"
            },
            {
               "type":"community",
               "url":"http:\/\/movies.nytimes.com\/movie\/27394\/King-Kong-vs-Godzilla\/rnr",
               "suggested_link_text":"Readers' Reviews of King Kong vs. Godzilla"
            },
            {
               "type":"trailers",
               "url":"http:\/\/movies.nytimes.com\/movie\/27394\/King-Kong-vs-Godzilla\/trailers",
               "suggested_link_text":"Trailers & Clips for King Kong vs. Godzilla"
            }
         ]
      }
   ]
}